extract_pages/__init__.py
extract_pages/_version.py
extract_pages/extract_pages.py
extract_pages/tests/__init__.py
extract_pages/tests/conftest.py
extract_pages/tests/test_extract.py
extract_pages/tests/test_data/diatonic-harmony-set.pdf
extract_pages/tests/test_data/fundamentals-set.pdf
extract_pages-0.1.0.dist-info/LICENSE
extract_pages-0.1.0.dist-info/METADATA
extract_pages-0.1.0.dist-info/WHEEL
extract_pages-0.1.0.dist-info/entry_points.txt
extract_pages-0.1.0.dist-info/top_level.txt
extract_pages-0.1.0.dist-info/RECORD
