Metadata-Version: 2.1
Name: extract-pages
Version: 0.1.0
Summary: Extract and combine pages from multiple pdf files
Home-page: https://github.com/mrakitin/extract-pages
Author: Maksim Rakitin
Author-email: 
License: BSD (3-clause)
Platform: UNKNOWN
Classifier: Development Status :: 2 - Pre-Alpha
Classifier: Natural Language :: English
Classifier: Programming Language :: Python :: 3
Requires-Python: >=3.6
License-File: LICENSE
Requires-Dist: PyPDF2
Requires-Dist: tqdm
